<?xml version="1.0" encoding="UTF-8"?>
<beans xmlns="http://www.springframework.org/schema/beans"
    xmlns:context="http://www.springframework.org/schema/context"
    xmlns:cxf="http://camel.apache.org/schema/cxf"
    xmlns:xsi="http://www.w3.org/2001/XMLSchema-instance" xsi:schemaLocation="        http://www.springframework.org/schema/beans http://www.springframework.org/schema/beans/spring-beans.xsd        http://camel.apache.org/schema/spring http://camel.apache.org/schema/spring/camel-spring.xsd        http://www.springframework.org/schema/context http://www.springframework.org/schema/context/spring-context.xsd        http://camel.apache.org/schema/cxf http://camel.apache.org/schema/cxf/camel-cxf.xsd        ">
    <camelContext id="rental-service" xmlns="http://camel.apache.org/schema/spring">
        <rest id="chuckrental" path="/chuckrental">
            <post id="rental-post" outType="nextgen.model.Rental"
                type="nextgen.apimodel.RentalEdit" uri="/save">
                <route>
                    <transform>
                        <method method="save" ref="rentalCRUD"/>
                    </transform>
                </route>
            </post>
            <get id="rental-find-all" uri="/findAll">
                <route>
                    <transform>
                        <method method="findAll" ref="rentalCRUD"/>
                    </transform>
                </route>
            </get>
            <get id="rental-find-by-id" outType="nextgen.model.Rental" uri="/findById/{id}">
                <route>
                    <log message="${header.id}"/>
                    <transform>
                        <method method="findById" ref="rentalCRUD"/>
                    </transform>
                </route>
            </get>
        </rest>
        <route id="http-receiver">
            <from id="http-receiver-starter" uri="servlet://ping"/>
            <setHeader headerName="Content-Type" id="_setHeader1">
                <constant>application/json</constant>
            </setHeader>
            <setBody id="_setBody1">
                <constant>{"msg" : "HELLO"}</constant>
            </setBody>
        </route>
    </camelContext>
</beans>
